{
    "m_Version": 12,
    "DisplayName": "Автомобили - Грузовики",
    "Icon": "Car",
    "Color": "FBFCFEFF",
    "IsExchange": 0,
    "InitStockPercent": 25,
    "Items": [
        {
            "ClassName": "Truck_01_Covered",
            "MaxPriceThreshold": 100000,
            "MinPriceThreshold": 50000,
            "SellPricePercent": -1,
            "MaxStockThreshold": 1,
            "MinStockThreshold": 1,
            "QuantityPercent": -1,
            "SpawnAttachments": [
                "LugWrench",
                "Wrench",
                "Screwdriver",
                "rag_car_jack",
                "truck_01_wheel",
                "truck_01_wheel",
                "truck_01_wheel",
                "truck_01_wheel",
                "truck_01_wheeldouble",
                "truck_01_wheeldouble",
                "truck_01_wheeldouble",
                "truck_01_wheeldouble",
                "truck_01_hood",
                "truck_01_door_1_1",
                "truck_01_door_2_1",
                "truckbattery",
                "headlighth7",
                "headlighth7"
            ],
            "Variants": [
                "Truck_01_Covered",
                "Truck_01_Covered_Blue",
                "Truck_01_Covered_Orange",
                "Truck_01_Covered_Green",
                "Truck_01_Covered_Red",
                "Truck_01_Covered_White",
                "Truck_01_Covered_Black",
                "Truck_01_Covered_Wine",
                "Truck_01_Covered_Lime",
                "Truck_01_Covered_Yellow",
                "Truck_01_Covered_YellowBright"
            ]
        },
        {
            "ClassName": "kraz_255B",
            "MaxPriceThreshold": 50000,
            "MinPriceThreshold": 15000,
            "SellPricePercent": -1,
            "MaxStockThreshold": 1,
            "MinStockThreshold": 1,
            "QuantityPercent": -1,
            "SpawnAttachments": [
                "LugWrench",
                "Wrench",
                "Screwdriver",
                "rag_car_jack",
                "kraz_255B_wheel",
                "kraz_255B_wheel",
                "kraz_255B_wheel",
                "kraz_255B_wheel",
                "kraz_255B_wheel",
                "kraz_255B_wheel",
                "kraz_255B_wheel",
                "kraz_255B_wheel",
                "kraz_255B_tent",
                "kraz_255B_doors_driver",
                "kraz_255B_doors_codriver",
                "kraz_255B_doors_trunk",
                "kraz_255B_doors_hood",
                "carradiator",
                "sparkplug",
                "truckbattery",
                "headlighth7",
                "headlighth7"
            ],
            "Variants": [
                "kraz_255B_yellow",
                "kraz_255B_blue"
            ]
        },
        {
            "ClassName": "kraz_255B_kung",
            "MaxPriceThreshold": 50000,
            "MinPriceThreshold": 15000,
            "SellPricePercent": -1,
            "MaxStockThreshold": 1,
            "MinStockThreshold": 1,
            "QuantityPercent": -1,
            "SpawnAttachments": [
                "LugWrench",
                "Wrench",
                "Screwdriver",
                "rag_car_jack",
                "kraz_255B_wheel",
                "kraz_255B_wheel",
                "kraz_255B_wheel",
                "kraz_255B_wheel",
                "kraz_255B_wheel",
                "kraz_255B_wheel",
                "kraz_255B_wheel",
                "kraz_255B_wheel",
                "Kraz_255B_doors_trunk_kung",
                "kraz_255B_doors_driver",
                "kraz_255B_doors_codriver",
                "kraz_255B_doors_trunk",
                "kraz_255B_doors_hood",
                "carradiator",
                "sparkplug",
                "truckbattery",
                "headlighth7",
                "headlighth7"
            ],
            "Variants": [
                "kraz_255B_kung_yellow",
                "kraz_255B_kung_blue"
            ]
        },
        {
            "ClassName": "GAZ_33081",
            "MaxPriceThreshold": 50000,
            "MinPriceThreshold": 15000,
            "SellPricePercent": -1,
            "MaxStockThreshold": 1,
            "MinStockThreshold": 1,
            "QuantityPercent": -1,
            "SpawnAttachments": [
                "LugWrench",
                "Wrench",
                "Screwdriver",
                "rag_car_jack",
                "GAZ_33081_wheel",
                "GAZ_33081_wheel",
                "GAZ_33081_wheel",
                "GAZ_33081_wheel",
                "GAZ_33081_wheel",
                "GAZ_33081_tent",
                "GAZ_33081_doors_driver",
                "GAZ_33081_doors_codriver",
                "GAZ_33081_doors_cargo1",
                "GAZ_33081_doors_cargo2",
                "GAZ_33081_doors_hood",
                "carradiator",
                "sparkplug",
                "truckbattery",
                "headlighth7",
                "headlighth7"
            ],
            "Variants": [
                "GAZ_33081_camo"
            ]
        },
        {
            "ClassName": "gaz_51",
            "MaxPriceThreshold": 50000,
            "MinPriceThreshold": 15000,
            "SellPricePercent": -1,
            "MaxStockThreshold": 1,
            "MinStockThreshold": 1,
            "QuantityPercent": -1,
            "SpawnAttachments": [
                "LugWrench",
                "Wrench",
                "Screwdriver",
                "rag_car_jack",
                "gaz_51_wheel",
                "gaz_51_wheel",
                "gaz_51_wheel",
                "gaz_51_WheelDouble",
                "gaz_51_WheelDouble",
                "gaz_51_tent",
                "gaz_51_doors_driver",
                "gaz_51_doors_codriver",
                "gaz_51_doors_hood",
                "carradiator",
                "sparkplug",
                "truckbattery",
                "headlighth7",
                "headlighth7"
            ],
            "Variants": []
        },
        {
            "ClassName": "Gaz_53RF",
            "MaxPriceThreshold": 50000,
            "MinPriceThreshold": 15000,
            "SellPricePercent": -1,
            "MaxStockThreshold": 1,
            "MinStockThreshold": 1,
            "QuantityPercent": -1,
            "SpawnAttachments": [
                "LugWrench",
                "Wrench",
                "Screwdriver",
                "rag_car_jack",
                "Gaz_53RF_wheel",
                "Gaz_53RF_wheel",
                "Gaz_53RF_wheel",
                "Gaz_53RF_WheelDouble",
                "Gaz_53RF_WheelDouble",
                "Gaz_53RF_doors_driver",
                "Gaz_53RF_doors_codriver",
                "Gaz_53RF_doors_hood",
                "Gaz_53RF_doors_trunk",
                "carradiator",
                "sparkplug",
                "truckbattery",
                "headlighth7",
                "headlighth7"
            ],
            "Variants": []
        },
        {
            "ClassName": "GAZ_66",
            "MaxPriceThreshold": 50000,
            "MinPriceThreshold": 15000,
            "SellPricePercent": -1,
            "MaxStockThreshold": 1,
            "MinStockThreshold": 1,
            "QuantityPercent": -1,
            "SpawnAttachments": [
                "LugWrench",
                "Wrench",
                "Screwdriver",
                "rag_car_jack",
                "GAZ_66_wheel",
                "GAZ_66_wheel",
                "GAZ_66_wheel",
                "GAZ_66_wheel",
                "GAZ_66_wheel",
                "GAZ_66_doors_driver",
                "GAZ_66_doors_codriver",
                "GAZ_66_doors_cargo3",
                "GAZ_66_doors_cargo4",
                "carradiator",
                "sparkplug",
                "truckbattery",
                "headlighth7",
                "headlighth7"
            ],
            "Variants": [
                "GAZ_66_camo",
                "GAZ_66_zima_camo"
            ]
        },
        {
            "ClassName": "GAZ_66_kuzov",
            "MaxPriceThreshold": 50000,
            "MinPriceThreshold": 15000,
            "SellPricePercent": -1,
            "MaxStockThreshold": 1,
            "MinStockThreshold": 1,
            "QuantityPercent": -1,
            "SpawnAttachments": [
                "LugWrench",
                "Wrench",
                "Screwdriver",
                "rag_car_jack",
                "GAZ_66_wheel",
                "GAZ_66_wheel",
                "GAZ_66_wheel",
                "GAZ_66_wheel",
                "GAZ_66_wheel",
                "GAZ_66_doors_driver",
                "GAZ_66_doors_codriver",
                "GAZ_66_doors_trunk",
                "carradiator",
                "sparkplug",
                "truckbattery",
                "headlighth7",
                "headlighth7"
            ],
            "Variants": [
                "GAZ_66_kuzov_camo",
                "GAZ_66_kuzov_zima_camo"
            ]
        },
        {
            "ClassName": "kamaz_4310RUS",
            "MaxPriceThreshold": 50000,
            "MinPriceThreshold": 15000,
            "SellPricePercent": -1,
            "MaxStockThreshold": 1,
            "MinStockThreshold": 1,
            "QuantityPercent": -1,
            "SpawnAttachments": [
                "LugWrench",
                "Wrench",
                "Screwdriver",
                "rag_car_jack",
                "kamaz_4310RUS_wheel",
                "kamaz_4310RUS_wheel",
                "kamaz_4310RUS_wheel",
                "kamaz_4310RUS_wheel",
                "kamaz_4310RUS_wheel",
                "kamaz_4310RUS_wheel",
                "kamaz_4310RUS_wheel",
                "kamaz_4310RUS_wheel",
                "kamaz_4310RUS_tent",
                "kamaz_4310RUS_doors_driver",
                "kamaz_4310RUS_doors_codriver",
                "kamaz_4310RUS_doors_hood",
                "carradiator",
                "sparkplug",
                "truckbattery",
                "headlighth7",
                "headlighth7"
            ],
            "Variants": [
                "kamaz_4310RUS_blue",
                "kamaz_4310RUS_orange"
            ]
        },
        {
            "ClassName": "kamaz_4310RUS_kung",
            "MaxPriceThreshold": 50000,
            "MinPriceThreshold": 15000,
            "SellPricePercent": -1,
            "MaxStockThreshold": 1,
            "MinStockThreshold": 1,
            "QuantityPercent": -1,
            "SpawnAttachments": [
                "LugWrench",
                "Wrench",
                "Screwdriver",
                "rag_car_jack",
                "kamaz_4310RUS_wheel",
                "kamaz_4310RUS_wheel",
                "kamaz_4310RUS_wheel",
                "kamaz_4310RUS_wheel",
                "kamaz_4310RUS_wheel",
                "kamaz_4310RUS_wheel",
                "kamaz_4310RUS_wheel",
                "kamaz_4310RUS_wheel",
                "kamaz_4310RUS_doors_driver",
                "kamaz_4310RUS_doors_codriver",
                "kamaz_4310RUS_doors_hood",
                "kamaz_4310RUS_doors_trunk",
                "carradiator",
                "sparkplug",
                "truckbattery",
                "headlighth7",
                "headlighth7"
            ],
            "Variants": [
                "kamaz_4310RUS_kung_blue",
                "kamaz_4310RUS_kung_orange",
                "kamaz_4310RUS_kung_oon"
            ]
        },
        {
            "ClassName": "URAL_375_1964",
            "MaxPriceThreshold": 50000,
            "MinPriceThreshold": 15000,
            "SellPricePercent": -1,
            "MaxStockThreshold": 1,
            "MinStockThreshold": 1,
            "QuantityPercent": -1,
            "SpawnAttachments": [
                "LugWrench",
                "Wrench",
                "Screwdriver",
                "rag_car_jack",
                "URAL_375_1964_wheel",
                "URAL_375_1964_wheel",
                "URAL_375_1964_wheel",
                "URAL_375_1964_wheel",
                "URAL_375_1964_wheel",
                "URAL_375_1964_wheel",
                "URAL_375_1964_wheel",
                "URAL_375_1964_wheel",
                "URAL_375_1964_tent",
                "URAL_375_1964_doors_driver",
                "URAL_375_1964_doors_codriver",
                "URAL_375_1964_doors_hood",
                "carradiator",
                "sparkplug",
                "truckbattery",
                "headlighth7",
                "headlighth7"
            ],
            "Variants": [
                "URAL_375_1964_zima",
                "URAL_375_1964_CDF"
            ]
        },
        {
            "ClassName": "ZIL_130",
            "MaxPriceThreshold": 50000,
            "MinPriceThreshold": 15000,
            "SellPricePercent": -1,
            "MaxStockThreshold": 1,
            "MinStockThreshold": 1,
            "QuantityPercent": -1,
            "SpawnAttachments": [
                "LugWrench",
                "Wrench",
                "Screwdriver",
                "rag_car_jack",
                "ZIL_130_wheel",
                "ZIL_130_wheel",
                "ZIL_130_wheel",
                "ZIL_130_WheelDouble",
                "ZIL_130_WheelDouble",
                "ZIL_130_tent",
                "ZIL_130_doors_driver",
                "ZIL_130_doors_codriver",
                "ZIL_130_doors_hood",
                "carradiator",
                "sparkplug",
                "truckbattery",
                "headlighth7",
                "headlighth7"
            ],
            "Variants": [
                "ZIL_130_green",
                "ZIL_130_CDF"
            ]
        },
        {
            "ClassName": "ZIL_130_kung",
            "MaxPriceThreshold": 50000,
            "MinPriceThreshold": 15000,
            "SellPricePercent": -1,
            "MaxStockThreshold": 1,
            "MinStockThreshold": 1,
            "QuantityPercent": -1,
            "SpawnAttachments": [
                "LugWrench",
                "Wrench",
                "Screwdriver",
                "rag_car_jack",
                "ZIL_130_wheel",
                "ZIL_130_wheel",
                "ZIL_130_wheel",
                "ZIL_130_WheelDouble",
                "ZIL_130_WheelDouble",
                "ZIL_130_doors_trunk",
                "ZIL_130_doors_driver",
                "ZIL_130_doors_codriver",
                "ZIL_130_doors_hood",
                "carradiator",
                "sparkplug",
                "truckbattery",
                "headlighth7",
                "headlighth7"
            ],
            "Variants": [
                "ZIL_130_kung_green"
            ]
        },
        {
            "ClassName": "ZIL_131",
            "MaxPriceThreshold": 50000,
            "MinPriceThreshold": 15000,
            "SellPricePercent": -1,
            "MaxStockThreshold": 1,
            "MinStockThreshold": 1,
            "QuantityPercent": -1,
            "SpawnAttachments": [
                "LugWrench",
                "Wrench",
                "Screwdriver",
                "rag_car_jack",
                "ZIL_131_wheel",
                "ZIL_131_wheel",
                "ZIL_131_wheel",
                "ZIL_131_wheel",
                "ZIL_131_wheel",
                "ZIL_131_wheel",
                "ZIL_131_wheel",
                "ZIL_131_doors_driver",
                "ZIL_131_doors_codriver",
                "ZIL_131_doors_trunk",
                "ZIL_131_doors_hood",
                "carradiator",
                "sparkplug",
                "truckbattery",
                "headlighth7",
                "headlighth7"
            ],
            "Variants": []
        },
        {
            "ClassName": "ZIL_131_tent",
            "MaxPriceThreshold": 50000,
            "MinPriceThreshold": 15000,
            "SellPricePercent": -1,
            "MaxStockThreshold": 1,
            "MinStockThreshold": 1,
            "QuantityPercent": -1,
            "SpawnAttachments": [
                "LugWrench",
                "Wrench",
                "Screwdriver",
                "rag_car_jack",
                "ZIL_131_wheel",
                "ZIL_131_wheel",
                "ZIL_131_wheel",
                "ZIL_131_wheel",
                "ZIL_131_wheel",
                "ZIL_131_wheel",
                "ZIL_131_wheel",
                "ZIL_131_tent_box",
                "ZIL_131_doors_driver",
                "ZIL_131_doors_codriver",
                "ZIL_131_tent_doors_trunk",
                "ZIL_131_doors_hood",
                "carradiator",
                "sparkplug",
                "truckbattery",
                "headlighth7",
                "headlighth7"
            ],
            "Variants": []
        },
        {
            "ClassName": "ZIL_157_rus",
            "MaxPriceThreshold": 50000,
            "MinPriceThreshold": 15000,
            "SellPricePercent": -1,
            "MaxStockThreshold": 1,
            "MinStockThreshold": 1,
            "QuantityPercent": -1,
            "SpawnAttachments": [
                "LugWrench",
                "Wrench",
                "Screwdriver",
                "rag_car_jack",
                "ZIL_157_rus_wheel",
                "ZIL_157_rus_wheel",
                "ZIL_157_rus_wheel",
                "ZIL_157_rus_GR_wheel",
                "ZIL_157_rus_GR_wheel",
                "ZIL_157_rus_GR_wheel",
                "ZIL_157_rus_GR_wheel",
                "ZIL_157_rus_tent",
                "ZIL_157_rus_doors_driver",
                "ZIL_157_rus_doors_codriver",
                "ZIL_157_rus_doors_hood",
                "ZIL_157_rus_doors_trunk",
                "carradiator",
                "sparkplug",
                "truckbattery",
                "headlighth7",
                "headlighth7"
            ],
            "Variants": [
                "ZIL_157_rus_gray",
                "ZIL_157_rus_yellow"
            ]
        },
        {
            "ClassName": "ZIL_157_kung_rus",
            "MaxPriceThreshold": 50000,
            "MinPriceThreshold": 15000,
            "SellPricePercent": -1,
            "MaxStockThreshold": 1,
            "MinStockThreshold": 1,
            "QuantityPercent": -1,
            "SpawnAttachments": [
                "LugWrench",
                "Wrench",
                "Screwdriver",
                "rag_car_jack",
                "ZIL_157_rus_wheel",
                "ZIL_157_rus_wheel",
                "ZIL_157_rus_wheel",
                "ZIL_157_rus_GR_wheel",
                "ZIL_157_rus_GR_wheel",
                "ZIL_157_rus_GR_wheel",
                "ZIL_157_rus_GR_wheel",
                "ZIL_157_rus_doors_driver",
                "ZIL_157_rus_doors_codriver",
                "ZIL_157_rus_doors_hood",
                "ZIL_157_rus_kung_doors_trunk",
                "carradiator",
                "sparkplug",
                "truckbattery",
                "headlighth7",
                "headlighth7"
            ],
            "Variants": [
                "ZIL_157_kung_rus_gray",
                "ZIL_157_kung_rus_yellow"
            ]
        }
    ]
}