<?xml version="1.0" encoding="UTF-8" standalone="yes" ?>
<spawnabletypes>
	<!-- ГРУЗОВАЯ ТЕХНИКА -->
	<!-- Vanila M3S -->
	<type name="Truck_01_Covered">
		<attachments chance="1.00">
			<item name="Truck_01_Wheel" chance="0.35" />
		</attachments>
		<attachments chance="1.00">
			<item name="Truck_01_Wheel" chance="0.35" />
		</attachments>
		<attachments chance="1.00">
			<item name="Truck_01_Wheel" chance="0.35" />
		</attachments>
		<attachments chance="1.00">
			<item name="Truck_01_Wheel" chance="0.35" />
		</attachments>
		<attachments chance="1.00">
			<item name="Truck_01_WheelDouble" chance="0.35" />
		</attachments>
		<attachments chance="1.00">
			<item name="Truck_01_WheelDouble" chance="0.35" />
		</attachments>
		<attachments chance="1.00">
			<item name="Truck_01_WheelDouble" chance="0.35" />
		</attachments>
		<attachments chance="1.00">
			<item name="Truck_01_WheelDouble" chance="0.35" />
		</attachments>
		<attachments chance="1.00">
			<item name="TruckBattery" chance="0.40" />
		</attachments>
		<attachments chance="1.00">
			<item name="HeadlightH7" chance="0.60" />
		</attachments>
		<attachments chance="1.00">
			<item name="HeadlightH7" chance="0.60" />
		</attachments>
		<attachments chance="1.00">
			<item name="Truck_01_Hood" chance="0.20" />
		</attachments>
		<attachments chance="1.00">
			<item name="Truck_01_Door_1_1" chance="0.35" />
		</attachments>
		<attachments chance="1.00">
			<item name="Truck_01_Door_2_1" chance="0.35" />
		</attachments>
	</type>

	<!-- RUSForma AEC Matador -->
	<type name="AEC_Matador">
		<attachments chance="1.00">
			<item name="AEC_Matador_Wheel" chance="0.35" />
		</attachments>
		<attachments chance="1.00">
			<item name="AEC_Matador_Wheel" chance="0.35" />
		</attachments>
		<attachments chance="1.00">
			<item name="AEC_Matador_Wheel" chance="0.35" />
		</attachments>
		<attachments chance="1.00">
			<item name="AEC_Matador_Wheel" chance="0.35" />
		</attachments>
		<attachments chance="1.00">
			<item name="AEC_Matador_Wheel" chance="0.20" />
		</attachments>
		<attachments chance="1.00">
			<item name="TruckBattery" chance="0.40" />
		</attachments>
		<attachments chance="1.00">
			<item name="CarRadiator" chance="0.40" />
		</attachments>
		<attachments chance="1.00">
			<item name="SparkPlug" chance="0.50" />
		</attachments>
		<attachments chance="1.00">
			<item name="HeadlightH7" chance="0.60" />
		</attachments>
		<attachments chance="1.00">
			<item name="HeadlightH7" chance="0.60" />
		</attachments>
		<attachments chance="1.00">
			<item name="AEC_Matador_doors_driver" chance="0.40" />
		</attachments>
		<attachments chance="1.00">
			<item name="AEC_Matador_doors_codriver" chance="0.40" />
		</attachments>
		<attachments chance="1.00">
			<item name="AEC_Matador_doors_cargo3" chance="0.40" />
		</attachments>
		<attachments chance="1.00">
			<item name="AEC_Matador_doors_trunk" chance="0.30" />
		</attachments>
		<attachments chance="1.00">
			<item name="AEC_Matador_doors_hood" chance="0.20" />
		</attachments>
		<attachments chance="1.00">
			<item name="AEC_Matador_tent" chance="0.50" />
		</attachments>
	</type>
	
	<!-- RUSForma Gaz 33081 Sadko -->
	<type name="Gaz_33081">
		<attachments chance="1.00">
			<item name="Gaz_33081_Wheel" chance="0.35" />
		</attachments>
		<attachments chance="1.00">
			<item name="Gaz_33081_Wheel" chance="0.35" />
		</attachments>
		<attachments chance="1.00">
			<item name="Gaz_33081_Wheel" chance="0.35" />
		</attachments>
		<attachments chance="1.00">
			<item name="Gaz_33081_Wheel" chance="0.35" />
		</attachments>
		<attachments chance="1.00">
			<item name="Gaz_33081_Wheel" chance="0.20" />
		</attachments>
		<attachments chance="1.00">
			<item name="TruckBattery" chance="0.40" />
		</attachments>
		<attachments chance="1.00">
			<item name="CarRadiator" chance="0.40" />
		</attachments>
		<attachments chance="1.00">
			<item name="SparkPlug" chance="0.50" />
		</attachments>
		<attachments chance="1.00">
			<item name="HeadlightH7" chance="0.60" />
		</attachments>
		<attachments chance="1.00">
			<item name="HeadlightH7" chance="0.60" />
		</attachments>
		<attachments chance="1.00">
			<item name="Gaz_33081_doors_driver" chance="0.40" />
		</attachments>
		<attachments chance="1.00">
			<item name="Gaz_33081_doors_codriver" chance="0.40" />
		</attachments>
		<attachments chance="1.00">
			<item name="Gaz_33081_doors_cargo1" chance="0.40" />
		</attachments>
		<attachments chance="1.00">
			<item name="Gaz_33081_doors_cargo2" chance="0.40" />
		</attachments>
		<attachments chance="1.00">
			<item name="Gaz_33081_doors_hood" chance="0.20" />
		</attachments>
		<attachments chance="1.00">
			<item name="Gaz_33081_tent" chance="0.50" />
		</attachments>
	</type>
	
	<!-- RUSForma Gaz 51 -->
	<type name="Gaz_51">
		<attachments chance="1.00">
			<item name="Gaz_51_Wheel" chance="0.35" />
		</attachments>
		<attachments chance="1.00">
			<item name="Gaz_51_Wheel" chance="0.35" />
		</attachments>
		<attachments chance="1.00">
			<item name="Gaz_51_WheelDouble" chance="0.35" />
		</attachments>
		<attachments chance="1.00">
			<item name="Gaz_51_WheelDouble" chance="0.35" />
		</attachments>
		<attachments chance="1.00">
			<item name="Gaz_51_Wheel" chance="0.20" />
		</attachments>
		<attachments chance="1.00">
			<item name="TruckBattery" chance="0.40" />
		</attachments>
		<attachments chance="1.00">
			<item name="CarRadiator" chance="0.40" />
		</attachments>
		<attachments chance="1.00">
			<item name="SparkPlug" chance="0.50" />
		</attachments>
		<attachments chance="1.00">
			<item name="HeadlightH7" chance="0.60" />
		</attachments>
		<attachments chance="1.00">
			<item name="HeadlightH7" chance="0.60" />
		</attachments>
		<attachments chance="1.00">
			<item name="Gaz_51_doors_driver" chance="0.40" />
		</attachments>
		<attachments chance="1.00">
			<item name="Gaz_51_doors_codriver" chance="0.40" />
		</attachments>
		<attachments chance="1.00">
			<item name="Gaz_51_doors_hood" chance="0.20" />
		</attachments>
		<attachments chance="1.00">
			<item name="Gaz_51_tent" chance="0.50" />
		</attachments>
	</type>
	
	<!-- RUSForma Gaz 53 RF -->
	<type name="Gaz_53RF">
		<attachments chance="1.00">
			<item name="Gaz_53RF_Wheel" chance="0.35" />
		</attachments>
		<attachments chance="1.00">
			<item name="Gaz_53RF_Wheel" chance="0.35" />
		</attachments>
		<attachments chance="1.00">
			<item name="Gaz_53RF_WheelDouble" chance="0.35" />
		</attachments>
		<attachments chance="1.00">
			<item name="Gaz_53RF_WheelDouble" chance="0.35" />
		</attachments>
		<attachments chance="1.00">
			<item name="Gaz_53RF_Wheel" chance="0.20" />
		</attachments>
		<attachments chance="1.00">
			<item name="TruckBattery" chance="0.40" />
		</attachments>
		<attachments chance="1.00">
			<item name="CarRadiator" chance="0.40" />
		</attachments>
		<attachments chance="1.00">
			<item name="SparkPlug" chance="0.50" />
		</attachments>
		<attachments chance="1.00">
			<item name="HeadlightH7" chance="0.60" />
		</attachments>
		<attachments chance="1.00">
			<item name="HeadlightH7" chance="0.60" />
		</attachments>
		<attachments chance="1.00">
			<item name="Gaz_53RF_doors_driver" chance="0.40" />
		</attachments>
		<attachments chance="1.00">
			<item name="Gaz_53RF_doors_codriver" chance="0.40" />
		</attachments>
		<attachments chance="1.00">
			<item name="Gaz_53RF_doors_hood" chance="0.20" />
		</attachments>
		<attachments chance="1.00">
			<item name="Gaz_53RF_doors_trunk" chance="0.30" />
		</attachments>
	</type>
	
	<!-- RUSForma Gaz 66 / 66 kuzov -->
	<type name="Gaz_66">
		<attachments chance="1.00">
			<item name="Gaz_66_Wheel" chance="0.35" />
		</attachments>
		<attachments chance="1.00">
			<item name="Gaz_66_Wheel" chance="0.35" />
		</attachments>
		<attachments chance="1.00">
			<item name="Gaz_66_Wheel" chance="0.35" />
		</attachments>
		<attachments chance="1.00">
			<item name="Gaz_66_Wheel" chance="0.35" />
		</attachments>
		<attachments chance="1.00">
			<item name="Gaz_66_Wheel" chance="0.20" />
		</attachments>
		<attachments chance="1.00">
			<item name="TruckBattery" chance="0.40" />
		</attachments>
		<attachments chance="1.00">
			<item name="CarRadiator" chance="0.40" />
		</attachments>
		<attachments chance="1.00">
			<item name="SparkPlug" chance="0.50" />
		</attachments>
		<attachments chance="1.00">
			<item name="HeadlightH7" chance="0.60" />
		</attachments>
		<attachments chance="1.00">
			<item name="HeadlightH7" chance="0.60" />
		</attachments>
		<attachments chance="1.00">
			<item name="Gaz_66_doors_driver" chance="0.40" />
		</attachments>
		<attachments chance="1.00">
			<item name="Gaz_66_doors_codriver" chance="0.40" />
		</attachments>
		<attachments chance="1.00">
			<item name="Gaz_66_doors_cargo3" chance="0.40" />
		</attachments>
		<attachments chance="1.00">
			<item name="Gaz_66_doors_cargo4" chance="0.40" />
		</attachments>
		<attachments chance="1.00">
			<item name="Gaz_66_doors_trunk" chance="0.30" />
		</attachments>
	</type>
	<type name="Gaz_66_kuzov">
		<attachments chance="1.00">
			<item name="Gaz_66_Wheel" chance="0.35" />
		</attachments>
		<attachments chance="1.00">
			<item name="Gaz_66_Wheel" chance="0.35" />
		</attachments>
		<attachments chance="1.00">
			<item name="Gaz_66_Wheel" chance="0.35" />
		</attachments>
		<attachments chance="1.00">
			<item name="Gaz_66_Wheel" chance="0.35" />
		</attachments>
		<attachments chance="1.00">
			<item name="Gaz_66_Wheel" chance="0.20" />
		</attachments>
		<attachments chance="1.00">
			<item name="TruckBattery" chance="0.40" />
		</attachments>
		<attachments chance="1.00">
			<item name="CarRadiator" chance="0.40" />
		</attachments>
		<attachments chance="1.00">
			<item name="SparkPlug" chance="0.50" />
		</attachments>
		<attachments chance="1.00">
			<item name="HeadlightH7" chance="0.60" />
		</attachments>
		<attachments chance="1.00">
			<item name="HeadlightH7" chance="0.60" />
		</attachments>
		<attachments chance="1.00">
			<item name="Gaz_66_doors_driver" chance="0.40" />
		</attachments>
		<attachments chance="1.00">
			<item name="Gaz_66_doors_codriver" chance="0.40" />
		</attachments>
	</type>
	
	<!-- RUSForma Kamaz 4310 Rus / 4310 Rus Kung -->
	<type name="Kamaz_4310RUS">
		<attachments chance="1.00">
			<item name="Kamaz_4310RUS_Wheel" chance="0.35" />
		</attachments>
		<attachments chance="1.00">
			<item name="Kamaz_4310RUS_Wheel" chance="0.35" />
		</attachments>
		<attachments chance="1.00">
			<item name="Kamaz_4310RUS_Wheel" chance="0.35" />
		</attachments>
		<attachments chance="1.00">
			<item name="Kamaz_4310RUS_Wheel" chance="0.35" />
		</attachments>
		<attachments chance="1.00">
			<item name="Kamaz_4310RUS_Wheel" chance="0.35" />
		</attachments>
		<attachments chance="1.00">
			<item name="Kamaz_4310RUS_Wheel" chance="0.35" />
		</attachments>
		<attachments chance="1.00">
			<item name="Kamaz_4310RUS_Wheel" chance="0.20" />
		</attachments>
		<attachments chance="1.00">
			<item name="Kamaz_4310RUS_Wheel" chance="0.20" />
		</attachments>
		<attachments chance="1.00">
			<item name="TruckBattery" chance="0.40" />
		</attachments>
		<attachments chance="1.00">
			<item name="CarRadiator" chance="0.40" />
		</attachments>
		<attachments chance="1.00">
			<item name="SparkPlug" chance="0.50" />
		</attachments>
		<attachments chance="1.00">
			<item name="HeadlightH7" chance="0.60" />
		</attachments>
		<attachments chance="1.00">
			<item name="HeadlightH7" chance="0.60" />
		</attachments>
		<attachments chance="1.00">
			<item name="Kamaz_4310RUS_doors_driver" chance="0.40" />
		</attachments>
		<attachments chance="1.00">
			<item name="Kamaz_4310RUS_doors_codriver" chance="0.40" />
		</attachments>
		<attachments chance="1.00">
			<item name="Kamaz_4310RUS_doors_hood" chance="0.20" />
		</attachments>
		<attachments chance="1.00">
			<item name="Kamaz_4310RUS_tent" chance="0.50" />
		</attachments>
	</type>
	<type name="Kamaz_4310RUS_kung">
		<attachments chance="1.00">
			<item name="Kamaz_4310RUS_Wheel" chance="0.35" />
		</attachments>
		<attachments chance="1.00">
			<item name="Kamaz_4310RUS_Wheel" chance="0.35" />
		</attachments>
		<attachments chance="1.00">
			<item name="Kamaz_4310RUS_Wheel" chance="0.35" />
		</attachments>
		<attachments chance="1.00">
			<item name="Kamaz_4310RUS_Wheel" chance="0.35" />
		</attachments>
		<attachments chance="1.00">
			<item name="Kamaz_4310RUS_Wheel" chance="0.35" />
		</attachments>
		<attachments chance="1.00">
			<item name="Kamaz_4310RUS_Wheel" chance="0.35" />
		</attachments>
		<attachments chance="1.00">
			<item name="Kamaz_4310RUS_Wheel" chance="0.20" />
		</attachments>
		<attachments chance="1.00">
			<item name="Kamaz_4310RUS_Wheel" chance="0.20" />
		</attachments>
		<attachments chance="1.00">
			<item name="TruckBattery" chance="0.40" />
		</attachments>
		<attachments chance="1.00">
			<item name="CarRadiator" chance="0.40" />
		</attachments>
		<attachments chance="1.00">
			<item name="SparkPlug" chance="0.50" />
		</attachments>
		<attachments chance="1.00">
			<item name="HeadlightH7" chance="0.60" />
		</attachments>
		<attachments chance="1.00">
			<item name="HeadlightH7" chance="0.60" />
		</attachments>
		<attachments chance="1.00">
			<item name="Kamaz_4310RUS_doors_driver" chance="0.40" />
		</attachments>
		<attachments chance="1.00">
			<item name="Kamaz_4310RUS_doors_codriver" chance="0.40" />
		</attachments>
		<attachments chance="1.00">
			<item name="Kamaz_4310RUS_doors_hood" chance="0.20" />
		</attachments>
		<attachments chance="1.00">
			<item name="Kamaz_4310RUS_trunk" chance="0.30" />
		</attachments>
	</type>
	
	<!-- RUSForma Kraz 255b / 255b Kung -->
	<type name="kraz_255B">
		<attachments chance="1.00">
			<item name="kraz_255B_Wheel" chance="0.35" />
		</attachments>
		<attachments chance="1.00">
			<item name="kraz_255B_Wheel" chance="0.35" />
		</attachments>
		<attachments chance="1.00">
			<item name="kraz_255B_Wheel" chance="0.35" />
		</attachments>
		<attachments chance="1.00">
			<item name="kraz_255B_Wheel" chance="0.35" />
		</attachments>
		<attachments chance="1.00">
			<item name="kraz_255B_Wheel" chance="0.35" />
		</attachments>
		<attachments chance="1.00">
			<item name="kraz_255B_Wheel" chance="0.35" />
		</attachments>
		<attachments chance="1.00">
			<item name="kraz_255B_Wheel" chance="0.20" />
		</attachments>
		<attachments chance="1.00">
			<item name="TruckBattery" chance="0.40" />
		</attachments>
		<attachments chance="1.00">
			<item name="CarRadiator" chance="0.40" />
		</attachments>
		<attachments chance="1.00">
			<item name="SparkPlug" chance="0.50" />
		</attachments>
		<attachments chance="1.00">
			<item name="HeadlightH7" chance="0.60" />
		</attachments>
		<attachments chance="1.00">
			<item name="HeadlightH7" chance="0.60" />
		</attachments>
		<attachments chance="1.00">
			<item name="kraz_255B_doors_driver" chance="0.40" />
		</attachments>
		<attachments chance="1.00">
			<item name="kraz_255B_doors_codriver" chance="0.40" />
		</attachments>
		<attachments chance="1.00">
			<item name="kraz_255B_doors_hood" chance="0.20" />
		</attachments>
		<attachments chance="1.00">
			<item name="kraz_255B_doors_trunk" chance="0.30" />
		</attachments>
		<attachments chance="1.00">
			<item name="kraz_255B_tent" chance="0.50" />
		</attachments>
	</type>
	<type name="kraz_255B_kung">
		<attachments chance="1.00">
			<item name="kraz_255B_Wheel" chance="0.35" />
		</attachments>
		<attachments chance="1.00">
			<item name="kraz_255B_Wheel" chance="0.35" />
		</attachments>
		<attachments chance="1.00">
			<item name="kraz_255B_Wheel" chance="0.35" />
		</attachments>
		<attachments chance="1.00">
			<item name="kraz_255B_Wheel" chance="0.35" />
		</attachments>
		<attachments chance="1.00">
			<item name="kraz_255B_Wheel" chance="0.35" />
		</attachments>
		<attachments chance="1.00">
			<item name="kraz_255B_Wheel" chance="0.35" />
		</attachments>
		<attachments chance="1.00">
			<item name="kraz_255B_Wheel" chance="0.20" />
		</attachments>
		<attachments chance="1.00">
			<item name="TruckBattery" chance="0.40" />
		</attachments>
		<attachments chance="1.00">
			<item name="CarRadiator" chance="0.40" />
		</attachments>
		<attachments chance="1.00">
			<item name="SparkPlug" chance="0.50" />
		</attachments>
		<attachments chance="1.00">
			<item name="HeadlightH7" chance="0.60" />
		</attachments>
		<attachments chance="1.00">
			<item name="HeadlightH7" chance="0.60" />
		</attachments>
		<attachments chance="1.00">
			<item name="kraz_255B_doors_driver" chance="0.40" />
		</attachments>
		<attachments chance="1.00">
			<item name="kraz_255B_doors_codriver" chance="0.40" />
		</attachments>
		<attachments chance="1.00">
			<item name="kraz_255B_doors_hood" chance="0.20" />
		</attachments>
		<attachments chance="1.00">
			<item name="kraz_255B_doors_trunk_kung" chance="0.30" />
		</attachments>
	</type>
	
	<!-- RUSForma Opel Blitz -->
	<type name="opel_blitz">
		<attachments chance="1.00">
			<item name="opel_blitz_Wheel" chance="0.35" />
		</attachments>
		<attachments chance="1.00">
			<item name="opel_blitz_Wheel" chance="0.35" />
		</attachments>
		<attachments chance="1.00">
			<item name="opel_blitz_WheelDouble" chance="0.35" />
		</attachments>
		<attachments chance="1.00">
			<item name="opel_blitz_WheelDouble" chance="0.35" />
		</attachments>
		<attachments chance="1.00">
			<item name="opel_blitz_Wheel" chance="0.20" />
		</attachments>
		<attachments chance="1.00">
			<item name="TruckBattery" chance="0.40" />
		</attachments>
		<attachments chance="1.00">
			<item name="CarRadiator" chance="0.40" />
		</attachments>
		<attachments chance="1.00">
			<item name="SparkPlug" chance="0.50" />
		</attachments>
		<attachments chance="1.00">
			<item name="HeadlightH7" chance="0.60" />
		</attachments>
		<attachments chance="1.00">
			<item name="HeadlightH7" chance="0.60" />
		</attachments>
		<attachments chance="1.00">
			<item name="opel_blitz_doors_driver" chance="0.40" />
		</attachments>
		<attachments chance="1.00">
			<item name="opel_blitz_doors_codriver" chance="0.40" />
		</attachments>
		<attachments chance="1.00">
			<item name="opel_blitz_doors_hood" chance="0.20" />
		</attachments>
		<attachments chance="1.00">
			<item name="opel_blitz_doors_cargo3" chance="0.20" />
		</attachments>
		<attachments chance="1.00">
			<item name="opel_blitz_doors_trunk" chance="0.30" />
		</attachments>
		<attachments chance="1.00">
			<item name="opel_blitz_tent" chance="0.50" />
		</attachments>
	</type>
	
	<!-- RUSForma URAL 375 (1964) -->
	<type name="URAL_375_1964">
		<attachments chance="1.00">
			<item name="URAL_375_1964_Wheel" chance="0.35" />
		</attachments>
		<attachments chance="1.00">
			<item name="URAL_375_1964_Wheel" chance="0.35" />
		</attachments>
		<attachments chance="1.00">
			<item name="URAL_375_1964_Wheel" chance="0.35" />
		</attachments>
		<attachments chance="1.00">
			<item name="URAL_375_1964_Wheel" chance="0.35" />
		</attachments>
		<attachments chance="1.00">
			<item name="URAL_375_1964_Wheel" chance="0.35" />
		</attachments>
		<attachments chance="1.00">
			<item name="URAL_375_1964_Wheel" chance="0.35" />
		</attachments>
		<attachments chance="1.00">
			<item name="URAL_375_1964_Wheel" chance="0.20" />
		</attachments>
		<attachments chance="1.00">
			<item name="URAL_375_1964_Wheel" chance="0.20" />
		</attachments>
		<attachments chance="1.00">
			<item name="TruckBattery" chance="0.40" />
		</attachments>
		<attachments chance="1.00">
			<item name="CarRadiator" chance="0.40" />
		</attachments>
		<attachments chance="1.00">
			<item name="SparkPlug" chance="0.50" />
		</attachments>
		<attachments chance="1.00">
			<item name="HeadlightH7" chance="0.60" />
		</attachments>
		<attachments chance="1.00">
			<item name="HeadlightH7" chance="0.60" />
		</attachments>
		<attachments chance="1.00">
			<item name="URAL_375_1964_doors_driver" chance="0.40" />
		</attachments>
		<attachments chance="1.00">
			<item name="URAL_375_1964_doors_codriver" chance="0.40" />
		</attachments>
		<attachments chance="1.00">
			<item name="URAL_375_1964_doors_hood" chance="0.20" />
		</attachments>
		<attachments chance="1.00">
			<item name="URAL_375_1964_tent" chance="0.50" />
		</attachments>
	</type>
	
	<!-- RUSForma Zil 133 -->
	<type name="ZIL133_double">
		<attachments chance="1.00">
			<item name="ZIL133_double_Wheel" chance="0.35" />
		</attachments>
		<attachments chance="1.00">
			<item name="ZIL133_double_Wheel" chance="0.35" />
		</attachments>
		<attachments chance="1.00">
			<item name="ZIL133_double_WheelDouble" chance="0.35" />
		</attachments>
		<attachments chance="1.00">
			<item name="ZIL133_double_WheelDouble" chance="0.35" />
		</attachments>
		<attachments chance="1.00">
			<item name="ZIL133_double_WheelDouble" chance="0.35" />
		</attachments>
		<attachments chance="1.00">
			<item name="ZIL133_double_WheelDouble" chance="0.35" />
		</attachments>
		<attachments chance="1.00">
			<item name="ZIL133_double_Wheel" chance="0.20" />
		</attachments>
		<attachments chance="1.00">
			<item name="TruckBattery" chance="0.40" />
		</attachments>
		<attachments chance="1.00">
			<item name="CarRadiator" chance="0.40" />
		</attachments>
		<attachments chance="1.00">
			<item name="SparkPlug" chance="0.50" />
		</attachments>
		<attachments chance="1.00">
			<item name="HeadlightH7" chance="0.60" />
		</attachments>
		<attachments chance="1.00">
			<item name="HeadlightH7" chance="0.60" />
		</attachments>
		<attachments chance="1.00">
			<item name="ZIL133_double_doors_driver" chance="0.40" />
		</attachments>
		<attachments chance="1.00">
			<item name="ZIL133_double_doors_codriver" chance="0.40" />
		</attachments>
		<attachments chance="1.00">
			<item name="ZIL133_double_doors_cargo1" chance="0.40" />
		</attachments>
		<attachments chance="1.00">
			<item name="ZIL133_double_doors_cargo2" chance="0.40" />
		</attachments>
		<attachments chance="1.00">
			<item name="ZIL133_double_doors_hood" chance="0.20" />
		</attachments>
		<attachments chance="1.00">
			<item name="ZIL133_double_doors_trunk" chance="0.30" />
		</attachments>
		<attachments chance="1.00">
			<item name="ZIL133_double_tent" chance="0.50" />
		</attachments>
	</type>
	
	<!-- RUSForma Zil 130 / 130 Kung -->
	<type name="ZIL_130">
		<attachments chance="1.00">
			<item name="ZIL_130_Wheel" chance="0.35" />
		</attachments>
		<attachments chance="1.00">
			<item name="ZIL_130_Wheel" chance="0.35" />
		</attachments>
		<attachments chance="1.00">
			<item name="ZIL_130_WheelDouble" chance="0.35" />
		</attachments>
		<attachments chance="1.00">
			<item name="ZIL_130_WheelDouble" chance="0.35" />
		</attachments>
		<attachments chance="1.00">
			<item name="ZIL_130_Wheel" chance="0.20" />
		</attachments>
		<attachments chance="1.00">
			<item name="TruckBattery" chance="0.40" />
		</attachments>
		<attachments chance="1.00">
			<item name="CarRadiator" chance="0.40" />
		</attachments>
		<attachments chance="1.00">
			<item name="SparkPlug" chance="0.50" />
		</attachments>
		<attachments chance="1.00">
			<item name="HeadlightH7" chance="0.60" />
		</attachments>
		<attachments chance="1.00">
			<item name="HeadlightH7" chance="0.60" />
		</attachments>
		<attachments chance="1.00">
			<item name="ZIL_130_doors_driver" chance="0.40" />
		</attachments>
		<attachments chance="1.00">
			<item name="ZIL_130_doors_codriver" chance="0.40" />
		</attachments>
		<attachments chance="1.00">
			<item name="ZIL_130_doors_hood" chance="0.20" />
		</attachments>
		<attachments chance="1.00">
			<item name="ZIL_130_tent" chance="0.50" />
		</attachments>
	</type>
	<type name="ZIL_130_kung">
		<attachments chance="1.00">
			<item name="ZIL_130_Wheel" chance="0.35" />
		</attachments>
		<attachments chance="1.00">
			<item name="ZIL_130_Wheel" chance="0.35" />
		</attachments>
		<attachments chance="1.00">
			<item name="ZIL_130_WheelDouble" chance="0.35" />
		</attachments>
		<attachments chance="1.00">
			<item name="ZIL_130_WheelDouble" chance="0.35" />
		</attachments>
		<attachments chance="1.00">
			<item name="ZIL_130_Wheel" chance="0.20" />
		</attachments>
		<attachments chance="1.00">
			<item name="TruckBattery" chance="0.40" />
		</attachments>
		<attachments chance="1.00">
			<item name="CarRadiator" chance="0.40" />
		</attachments>
		<attachments chance="1.00">
			<item name="SparkPlug" chance="0.50" />
		</attachments>
		<attachments chance="1.00">
			<item name="HeadlightH7" chance="0.60" />
		</attachments>
		<attachments chance="1.00">
			<item name="HeadlightH7" chance="0.60" />
		</attachments>
		<attachments chance="1.00">
			<item name="ZIL_130_doors_driver" chance="0.40" />
		</attachments>
		<attachments chance="1.00">
			<item name="ZIL_130_doors_codriver" chance="0.40" />
		</attachments>
		<attachments chance="1.00">
			<item name="ZIL_130_doors_hood" chance="0.20" />
		</attachments>
		<attachments chance="1.00">
			<item name="ZIL_130_doors_trunk" chance="0.30" />
		</attachments>
	</type>
	
	<!-- RUSForma Zil 131 / 131 Kung -->
	<type name="ZIL_131">
		<attachments chance="1.00">
			<item name="ZIL_131_Wheel" chance="0.35" />
		</attachments>
		<attachments chance="1.00">
			<item name="ZIL_131_Wheel" chance="0.35" />
		</attachments>
		<attachments chance="1.00">
			<item name="ZIL_131_Wheel" chance="0.35" />
		</attachments>
		<attachments chance="1.00">
			<item name="ZIL_131_Wheel" chance="0.35" />
		</attachments>
		<attachments chance="1.00">
			<item name="ZIL_131_Wheel" chance="0.35" />
		</attachments>
		<attachments chance="1.00">
			<item name="ZIL_131_Wheel" chance="0.35" />
		</attachments>
		<attachments chance="1.00">
			<item name="ZIL_131_Wheel" chance="0.20" />
		</attachments>
		<attachments chance="1.00">
			<item name="TruckBattery" chance="0.40" />
		</attachments>
		<attachments chance="1.00">
			<item name="CarRadiator" chance="0.40" />
		</attachments>
		<attachments chance="1.00">
			<item name="SparkPlug" chance="0.50" />
		</attachments>
		<attachments chance="1.00">
			<item name="HeadlightH7" chance="0.60" />
		</attachments>
		<attachments chance="1.00">
			<item name="HeadlightH7" chance="0.60" />
		</attachments>
		<attachments chance="1.00">
			<item name="ZIL_131_doors_driver" chance="0.40" />
		</attachments>
		<attachments chance="1.00">
			<item name="ZIL_131_doors_codriver" chance="0.40" />
		</attachments>
		<attachments chance="1.00">
			<item name="ZIL_131_doors_cargo4" chance="0.40" />
		</attachments>
		<attachments chance="1.00">
			<item name="ZIL_131_doors_hood" chance="0.20" />
		</attachments>
		<attachments chance="1.00">
			<item name="ZIL_131_doors_trunk" chance="0.30" />
		</attachments>
	</type>
	<type name="ZIL_131_tent">
		<attachments chance="1.00">
			<item name="ZIL_131_Wheel" chance="0.35" />
		</attachments>
		<attachments chance="1.00">
			<item name="ZIL_131_Wheel" chance="0.35" />
		</attachments>
		<attachments chance="1.00">
			<item name="ZIL_131_Wheel" chance="0.35" />
		</attachments>
		<attachments chance="1.00">
			<item name="ZIL_131_Wheel" chance="0.35" />
		</attachments>
		<attachments chance="1.00">
			<item name="ZIL_131_Wheel" chance="0.35" />
		</attachments>
		<attachments chance="1.00">
			<item name="ZIL_131_Wheel" chance="0.35" />
		</attachments>
		<attachments chance="1.00">
			<item name="ZIL_131_Wheel" chance="0.20" />
		</attachments>
		<attachments chance="1.00">
			<item name="TruckBattery" chance="0.40" />
		</attachments>
		<attachments chance="1.00">
			<item name="CarRadiator" chance="0.40" />
		</attachments>
		<attachments chance="1.00">
			<item name="SparkPlug" chance="0.50" />
		</attachments>
		<attachments chance="1.00">
			<item name="HeadlightH7" chance="0.60" />
		</attachments>
		<attachments chance="1.00">
			<item name="HeadlightH7" chance="0.60" />
		</attachments>
		<attachments chance="1.00">
			<item name="ZIL_131_doors_driver" chance="0.40" />
		</attachments>
		<attachments chance="1.00">
			<item name="ZIL_131_doors_codriver" chance="0.40" />
		</attachments>
		<attachments chance="1.00">
			<item name="ZIL_131_doors_hood" chance="0.20" />
		</attachments>
		<attachments chance="1.00">
			<item name="ZIL_131_tent_box" chance="0.50" />
		</attachments>
	</type>
	
	<!-- RUSForma Zil 157 RUS / 157 RUS Kung -->
	<type name="ZIL_157_rus">
		<attachments chance="1.00">
			<item name="ZIL_157_rus_Wheel" chance="0.35" />
		</attachments>
		<attachments chance="1.00">
			<item name="ZIL_157_rus_Wheel" chance="0.35" />
		</attachments>
		<attachments chance="1.00">
			<item name="ZIL_157_rus_Wheel" chance="0.35" />
		</attachments>
		<attachments chance="1.00">
			<item name="ZIL_157_rus_Wheel" chance="0.35" />
		</attachments>
		<attachments chance="1.00">
			<item name="ZIL_157_rus_Wheel" chance="0.35" />
		</attachments>
		<attachments chance="1.00">
			<item name="ZIL_157_rus_Wheel" chance="0.35" />
		</attachments>
		<attachments chance="1.00">
			<item name="ZIL_157_rus_Wheel" chance="0.20" />
		</attachments>
		<attachments chance="1.00">
			<item name="TruckBattery" chance="0.40" />
		</attachments>
		<attachments chance="1.00">
			<item name="CarRadiator" chance="0.40" />
		</attachments>
		<attachments chance="1.00">
			<item name="SparkPlug" chance="0.50" />
		</attachments>
		<attachments chance="1.00">
			<item name="HeadlightH7" chance="0.60" />
		</attachments>
		<attachments chance="1.00">
			<item name="HeadlightH7" chance="0.60" />
		</attachments>
		<attachments chance="1.00">
			<item name="ZIL_157_rus_doors_driver" chance="0.40" />
		</attachments>
		<attachments chance="1.00">
			<item name="ZIL_157_rus_doors_codriver" chance="0.40" />
		</attachments>
		<attachments chance="1.00">
			<item name="ZIL_157_rus_doors_hood" chance="0.20" />
		</attachments>
		<attachments chance="1.00">
			<item name="ZIL_157_rus_doors_trunk" chance="0.30" />
		</attachments>
		<attachments chance="1.00">
			<item name="ZIL_131_tent" chance="0.50" />
		</attachments>
	</type>
	<type name="ZIL_157_kung_rus">
		<attachments chance="1.00">
			<item name="ZIL_157_rus_Wheel" chance="0.35" />
		</attachments>
		<attachments chance="1.00">
			<item name="ZIL_157_rus_Wheel" chance="0.35" />
		</attachments>
		<attachments chance="1.00">
			<item name="ZIL_157_rus_Wheel" chance="0.35" />
		</attachments>
		<attachments chance="1.00">
			<item name="ZIL_157_rus_Wheel" chance="0.35" />
		</attachments>
		<attachments chance="1.00">
			<item name="ZIL_157_rus_Wheel" chance="0.35" />
		</attachments>
		<attachments chance="1.00">
			<item name="ZIL_157_rus_Wheel" chance="0.35" />
		</attachments>
		<attachments chance="1.00">
			<item name="ZIL_157_rus_Wheel" chance="0.20" />
		</attachments>
		<attachments chance="1.00">
			<item name="TruckBattery" chance="0.40" />
		</attachments>
		<attachments chance="1.00">
			<item name="CarRadiator" chance="0.40" />
		</attachments>
		<attachments chance="1.00">
			<item name="SparkPlug" chance="0.50" />
		</attachments>
		<attachments chance="1.00">
			<item name="HeadlightH7" chance="0.60" />
		</attachments>
		<attachments chance="1.00">
			<item name="HeadlightH7" chance="0.60" />
		</attachments>
		<attachments chance="1.00">
			<item name="ZIL_157_rus_doors_driver" chance="0.40" />
		</attachments>
		<attachments chance="1.00">
			<item name="ZIL_157_rus_doors_codriver" chance="0.40" />
		</attachments>
		<attachments chance="1.00">
			<item name="ZIL_157_rus_doors_hood" chance="0.20" />
		</attachments>
		<attachments chance="1.00">
			<item name="ZIL_157_rus_kung_doors_trunk" chance="0.30" />
		</attachments>
	</type>
	
	<!-- RUSForma Zis 5 Bortovoi -->
	<type name="ZiS5_kung">
		<attachments chance="1.00">
			<item name="ZiS5_Benzovoz_wheel" chance="0.35" />
		</attachments>
		<attachments chance="1.00">
			<item name="ZiS5_Benzovoz_wheel" chance="0.35" />
		</attachments>
		<attachments chance="1.00">
			<item name="ZiS5_Benzovoz_wheelDouble" chance="0.35" />
		</attachments>
		<attachments chance="1.00">
			<item name="ZiS5_Benzovoz_wheelDouble" chance="0.35" />
		</attachments>
		<attachments chance="1.00">
			<item name="ZiS5_Benzovoz_wheel" chance="0.20" />
		</attachments>
		<attachments chance="1.00">
			<item name="TruckBattery" chance="0.40" />
		</attachments>
		<attachments chance="1.00">
			<item name="CarRadiator" chance="0.40" />
		</attachments>
		<attachments chance="1.00">
			<item name="SparkPlug" chance="0.50" />
		</attachments>
		<attachments chance="1.00">
			<item name="HeadlightH7" chance="0.60" />
		</attachments>
		<attachments chance="1.00">
			<item name="HeadlightH7" chance="0.60" />
		</attachments>
		<attachments chance="1.00">
			<item name="ZiS5_Benzovoz_doors_driver" chance="0.40" />
		</attachments>
		<attachments chance="1.00">
			<item name="ZiS5_Benzovoz_doors_codriver" chance="0.40" />
		</attachments>
		<attachments chance="1.00">
			<item name="ZiS5_Benzovoz_doors_hood" chance="0.20" />
		</attachments>
		<attachments chance="1.00">
			<item name="ZiS5_Kung_tent" chance="0.50" />
		</attachments>
	</type>
</spawnabletypes>