{
    "DefaultWeatherPreset": "clear",
    "WeatherPresets": {
        "clear": {
            "m_WeatherChance": 30,
            "m_TransitionTime_Min": 300,
            "m_TransitionTime_Max": 480,
            "m_MinDuration_Min": 1200,
            "m_MinDuration_Max": 2400,
            "m_Overcast_Min": 0,
            "m_Overcast_Max": 0.2,
            "m_Fog_Min": 0,
            "m_Fog_Max": 0.1,
            "m_Rain_Min": 0,
            "m_Rain_Max": 0,
            "m_Snowfall_Min": 0,
            "m_Snowfall_Max": 0,
            "m_WindSpeed_Min": 0.3,
            "m_WindSpeed_Max": 1.5,
            "m_WindDirection_Min": 0,
            "m_WindDirection_Max": 360,
            "m_WindFunc_Min": 0.3,
            "m_WindFunc_Max": 0.6,
            "m_WindFunc_Speed": 120.0,
            "m_UseDynVolFog": 0,
            "m_VolFogDistanceDensity_Min": 0,
            "m_VolFogDistanceDensity_Max": 0,
            "m_VolFogHeightDensity_Min": 0,
            "m_VolFogHeightDensity_Max": 0,
            "m_VolFogHeightBias": 0,
            "m_FogTransitionTime": 30,
            "m_UseSnowflakeScale": 0,
            "m_SnowflakeScale_Min": 1,
            "m_SnowflakeScale_Max": 1,
            "m_SnowfallThreshold_Min": 0.7,
            "m_SnowfallThreshold_Max": 1,
            "m_SnowfallThreshold_Timeout": 60,
            "m_RainThreshold_Min": 0.7,
            "m_RainThreshold_Max": 1.0,
            "m_RainThreshold_Timeout": 60,
            "m_ThunderstormDensity": 0,
            "m_ThunderstormThreshold": 0.95,
            "m_LightningTimeout": 45,
            "m_UseEnvironmentTemperature": 0,
            "m_EnvironmentTemperature": 12
        },
        "partly_cloudy": {
            "m_WeatherChance": 25,
            "m_TransitionTime_Min": 300,
            "m_TransitionTime_Max": 480,
            "m_MinDuration_Min": 900,
            "m_MinDuration_Max": 1800,
            "m_Overcast_Min": 0.2,
            "m_Overcast_Max": 0.5,
            "m_Fog_Min": 0,
            "m_Fog_Max": 0,
            "m_Rain_Min": 0,
            "m_Rain_Max": 0,
            "m_Snowfall_Min": 0,
            "m_Snowfall_Max": 0,
            "m_WindSpeed_Min": 1,
            "m_WindSpeed_Max": 3,
            "m_WindDirection_Min": 0,
            "m_WindDirection_Max": 360,
            "m_WindFunc_Min": 0.3,
            "m_WindFunc_Max": 0.6,
            "m_WindFunc_Speed": 120.0,
            "m_UseDynVolFog": 0,
            "m_VolFogDistanceDensity_Min": 0,
            "m_VolFogDistanceDensity_Max": 0,
            "m_VolFogHeightDensity_Min": 0,
            "m_VolFogHeightDensity_Max": 0,
            "m_VolFogHeightBias": 0,
            "m_FogTransitionTime": 30,
            "m_UseSnowflakeScale": 0,
            "m_SnowflakeScale_Min": 1,
            "m_SnowflakeScale_Max": 1,
            "m_SnowfallThreshold_Min": 0.7,
            "m_SnowfallThreshold_Max": 1,
            "m_SnowfallThreshold_Timeout": 60,
            "m_RainThreshold_Min": 0.7,
            "m_RainThreshold_Max": 1.0,
            "m_RainThreshold_Timeout": 60,
            "m_ThunderstormDensity": 0.05,
            "m_ThunderstormThreshold": 0.95,
            "m_LightningTimeout": 60,
            "m_UseEnvironmentTemperature": 0,
            "m_EnvironmentTemperature": 15
        },
        "overcast": {
            "m_WeatherChance": 18,
            "m_TransitionTime_Min": 300,
            "m_TransitionTime_Max": 480,
            "m_MinDuration_Min": 900,
            "m_MinDuration_Max": 1800,
            "m_Overcast_Min": 0.5,
            "m_Overcast_Max": 0.7,
            "m_Fog_Min": 0,
            "m_Fog_Max": 0.1,
            "m_Rain_Min": 0,
            "m_Rain_Max": 0,
            "m_Snowfall_Min": 0,
            "m_Snowfall_Max": 0,
            "m_WindSpeed_Min": 2,
            "m_WindSpeed_Max": 5,
            "m_WindDirection_Min": 0,
            "m_WindDirection_Max": 360,
            "m_WindFunc_Min": 0.3,
            "m_WindFunc_Max": 0.6,
            "m_WindFunc_Speed": 120.0,
            "m_UseDynVolFog": 0,
            "m_VolFogDistanceDensity_Min": 0,
            "m_VolFogDistanceDensity_Max": 0,
            "m_VolFogHeightDensity_Min": 0,
            "m_VolFogHeightDensity_Max": 0,
            "m_VolFogHeightBias": 0,
            "m_FogTransitionTime": 30,
            "m_UseSnowflakeScale": 0,
            "m_SnowflakeScale_Min": 1,
            "m_SnowflakeScale_Max": 1,
            "m_SnowfallThreshold_Min": 0.7,
            "m_SnowfallThreshold_Max": 1,
            "m_SnowfallThreshold_Timeout": 60,
            "m_RainThreshold_Min": 0.7,
            "m_RainThreshold_Max": 1.0,
            "m_RainThreshold_Timeout": 60,
            "m_ThunderstormDensity": 0,
            "m_ThunderstormThreshold": 0.95,
            "m_LightningTimeout": 45,
            "m_UseEnvironmentTemperature": 0,
            "m_EnvironmentTemperature": 10
        },
        "rain": {
            "m_WeatherChance": 10,
            "m_TransitionTime_Min": 240,
            "m_TransitionTime_Max": 360,
            "m_MinDuration_Min": 600,
            "m_MinDuration_Max": 1200,
            "m_Overcast_Min": 0.7,
            "m_Overcast_Max": 0.85,
            "m_Fog_Min": 0,
            "m_Fog_Max": 0.15,
            "m_Rain_Min": 0.3,
            "m_Rain_Max": 0.7,
            "m_Snowfall_Min": 0,
            "m_Snowfall_Max": 0,
            "m_WindSpeed_Min": 3,
            "m_WindSpeed_Max": 7,
            "m_WindDirection_Min": 0,
            "m_WindDirection_Max": 360,
            "m_WindFunc_Min": 0.3,
            "m_WindFunc_Max": 0.6,
            "m_WindFunc_Speed": 120.0,
            "m_UseDynVolFog": 0,
            "m_VolFogDistanceDensity_Min": 0,
            "m_VolFogDistanceDensity_Max": 0,
            "m_VolFogHeightDensity_Min": 0,
            "m_VolFogHeightDensity_Max": 0,
            "m_VolFogHeightBias": 0,
            "m_FogTransitionTime": 30,
            "m_UseSnowflakeScale": 0,
            "m_SnowflakeScale_Min": 1,
            "m_SnowflakeScale_Max": 1,
            "m_SnowfallThreshold_Min": 0.7,
            "m_SnowfallThreshold_Max": 1,
            "m_SnowfallThreshold_Timeout": 60,
            "m_RainThreshold_Min": 0.7,
            "m_RainThreshold_Max": 1.0,
            "m_RainThreshold_Timeout": 60,
            "m_ThunderstormDensity": 0.05,
            "m_ThunderstormThreshold": 0.85,
            "m_LightningTimeout": 50,
            "m_UseEnvironmentTemperature": 0,
            "m_EnvironmentTemperature": 8
        },
        "stormy": {
            "m_WeatherChance": 2,
            "m_TransitionTime_Min": 240,
            "m_TransitionTime_Max": 360,
            "m_MinDuration_Min": 300,
            "m_MinDuration_Max": 600,
            "m_Overcast_Min": 0.85,
            "m_Overcast_Max": 1,
            "m_Fog_Min": 0,
            "m_Fog_Max": 0.15,
            "m_Rain_Min": 0.5,
            "m_Rain_Max": 1,
            "m_Snowfall_Min": 0,
            "m_Snowfall_Max": 0,
            "m_WindSpeed_Min": 8,
            "m_WindSpeed_Max": 14,
            "m_WindDirection_Min": 0,
            "m_WindDirection_Max": 360,
            "m_WindFunc_Min": 0.3,
            "m_WindFunc_Max": 0.6,
            "m_WindFunc_Speed": 120.0,
            "m_UseDynVolFog": 0,
            "m_VolFogDistanceDensity_Min": 0.1,
            "m_VolFogDistanceDensity_Max": 0.2,
            "m_VolFogHeightDensity_Min": 0.1,
            "m_VolFogHeightDensity_Max": 0.2,
            "m_VolFogHeightBias": 20,
            "m_FogTransitionTime": 40,
            "m_UseSnowflakeScale": 0,
            "m_SnowflakeScale_Min": 1,
            "m_SnowflakeScale_Max": 1,
            "m_SnowfallThreshold_Min": 0.7,
            "m_SnowfallThreshold_Max": 1,
            "m_SnowfallThreshold_Timeout": 60,
            "m_RainThreshold_Min": 0.7,
            "m_RainThreshold_Max": 1.0,
            "m_RainThreshold_Timeout": 60,
            "m_ThunderstormDensity": 0.2,
            "m_ThunderstormThreshold": 0.75,
            "m_LightningTimeout": 25,
            "m_UseEnvironmentTemperature": 0,
            "m_EnvironmentTemperature": 6
        },
        "foggy": {
            "m_WeatherChance": 8,
            "m_TransitionTime_Min": 300,
            "m_TransitionTime_Max": 480,
            "m_MinDuration_Min": 900,
            "m_MinDuration_Max": 1800,
            "m_Overcast_Min": 0.3,
            "m_Overcast_Max": 0.6,
            "m_Fog_Min": 0,
            "m_Fog_Max": 0,
            "m_Rain_Min": 0,
            "m_Rain_Max": 0,
            "m_Snowfall_Min": 0,
            "m_Snowfall_Max": 0,
            "m_WindSpeed_Min": 0.3,
            "m_WindSpeed_Max": 1.5,
            "m_WindDirection_Min": 0,
            "m_WindDirection_Max": 360,
            "m_WindFunc_Min": 0.3,
            "m_WindFunc_Max": 0.6,
            "m_WindFunc_Speed": 120.0,
            "m_UseDynVolFog": 1,
            "m_VolFogDistanceDensity_Min": 0.4,
            "m_VolFogDistanceDensity_Max": 0.7,
            "m_VolFogHeightDensity_Min": 0.3,
            "m_VolFogHeightDensity_Max": 0.6,
            "m_VolFogHeightBias": 0,
            "m_FogTransitionTime": 60,
            "m_UseSnowflakeScale": 0,
            "m_SnowflakeScale_Min": 1,
            "m_SnowflakeScale_Max": 1,
            "m_SnowfallThreshold_Min": 0.7,
            "m_SnowfallThreshold_Max": 1,
            "m_SnowfallThreshold_Timeout": 60,
            "m_RainThreshold_Min": 0.7,
            "m_RainThreshold_Max": 1.0,
            "m_RainThreshold_Timeout": 60,
            "m_ThunderstormDensity": 0,
            "m_ThunderstormThreshold": 0.95,
            "m_LightningTimeout": 45,
            "m_UseEnvironmentTemperature": 0,
            "m_EnvironmentTemperature": 5
        },
        "snowy": {
            "m_WeatherChance": 5,
            "m_TransitionTime_Min": 240,
            "m_TransitionTime_Max": 420,
            "m_MinDuration_Min": 600,
            "m_MinDuration_Max": 1200,
            "m_Overcast_Min": 0.6,
            "m_Overcast_Max": 0.85,
            "m_Fog_Min": 0,
            "m_Fog_Max": 0.1,
            "m_Rain_Min": 0,
            "m_Rain_Max": 0,
            "m_Snowfall_Min": 0.3,
            "m_Snowfall_Max": 0.6,
            "m_WindSpeed_Min": 2,
            "m_WindSpeed_Max": 5,
            "m_WindDirection_Min": 0,
            "m_WindDirection_Max": 360,
            "m_WindFunc_Min": 0.3,
            "m_WindFunc_Max": 0.6,
            "m_WindFunc_Speed": 120.0,
            "m_UseDynVolFog": 0,
            "m_VolFogDistanceDensity_Min": 0,
            "m_VolFogDistanceDensity_Max": 0,
            "m_VolFogHeightDensity_Min": 0,
            "m_VolFogHeightDensity_Max": 0,
            "m_VolFogHeightBias": 0,
            "m_FogTransitionTime": 30,
            "m_UseSnowflakeScale": 1,
            "m_SnowflakeScale_Min": 1,
            "m_SnowflakeScale_Max": 1.5,
            "m_SnowfallThreshold_Min": 0.4,
            "m_SnowfallThreshold_Max": 1,
            "m_SnowfallThreshold_Timeout": 15,
            "m_RainThreshold_Min": 0.7,
            "m_RainThreshold_Max": 1.0,
            "m_RainThreshold_Timeout": 60,
            "m_ThunderstormDensity": 0,
            "m_ThunderstormThreshold": 0.95,
            "m_LightningTimeout": 45,
            "m_UseEnvironmentTemperature": 1,
            "m_EnvironmentTemperature": -3
        }
    }
}
